<?xml version="1.0" encoding="utf-16"?>
<Level width="2">
  <Camera x="0" y="2" minWidth="20" maxWidth="30" />
  <Birds>
    <Bird type="BirdBlue" />
    <Bird type="BirdBlue" />
    <Bird type="BirdYellow" />
</Birds>
  <Slingshot x="-8" y="-2.5" />
  <GameObjects>
    <Block type="RectFat" material="ice" x="-2.56" y="3.735" rotation="90" />
    <Block type="RectFat" material="ice" x="-1.93" y="3.735" rotation="90" />
    <Block type="RectFat" material="wood" x="-0.97" y="3.735" rotation="90" />
    <Block type="RectFat" material="wood" x="-0.34" y="3.735" rotation="90" />
    <Block type="RectSmall" material="wood" x="-2.245" y="4.27" rotation="0" />
    <Block type="RectSmall" material="wood" x="-0.655" y="4.27" rotation="0" />
    <Block type="CircleSmall" material="wood" x="-2.528333" y="4.605" rotation="0" />
    <Pig type="BasicSmall" x="-0.655" y="4.63" rotation="0" />
    <Pig type="BasicSmall" x="-1.46" y="3.56" rotation="0" />
    <TNT type="TNT" x="-1.961667" y="4.63" rotation="0" />
    <Platform type="Platform" x="-2.69" y="3" rotation="0" scaleX="1" scaleY="1" />
    <Platform type="Platform" x="-2.07" y="3" rotation="0" scaleX="1" scaleY="1" />
    <Platform type="Platform" x="-1.45" y="3" rotation="0" scaleX="1" scaleY="1" />
    <Platform type="Platform" x="-0.83" y="3" rotation="0" scaleX="1" scaleY="1" />
    <Platform type="Platform" x="-0.21" y="3" rotation="0" scaleX="1" scaleY="1" />
    <Trigger type="Trigger" x="-2.659747" y="4.205177" />
</GameObjects>
</Level>
